[
  {
    "id": "temp",
    "name": "Template App",
    "icon": "/MyOS/apps/template/icon.svg",
    "html": "/MyOS/apps/template/app.html",
    "css": "/MyOS/apps/template/app.css",
    "js": "/MyOS/apps/template/app.js"
  },
  {
    "id": "gallery",
    "name": "Gallery App",
    "icon": "/MyOS/apps/apps/MyOS-Gallery-App/icon.svg",
    "html": "/MyOS/apps/apps/MyOS-Gallery-App/app.html",
    "css": "/MyOS/apps/apps/MyOS-Gallery-App/app.css",
    "js": "/MyOS/apps/apps/MyOS-Gallery-App/app.js"
  }
]